dldb_pd_column/__init__.py
dldb_pd_column/example.py
example_pkg_dldb_pd_columns-0.0.2.dist-info/METADATA
example_pkg_dldb_pd_columns-0.0.2.dist-info/WHEEL
example_pkg_dldb_pd_columns-0.0.2.dist-info/license.txt
example_pkg_dldb_pd_columns-0.0.2.dist-info/top_level.txt
example_pkg_dldb_pd_columns-0.0.2.dist-info/RECORD
